pynasonde/__init__.py
pynasonde/config.toml
pynasonde/digisonde_station_codes.csv
pynasonde/saoxml.dtd
pynasonde/webhook.py
pynasonde/digisonde/__init__.py
pynasonde/digisonde/digi_plots.py
pynasonde/digisonde/digi_utils.py
pynasonde/digisonde/datatypes/__init__.py
pynasonde/digisonde/datatypes/dftdatatypes.py
pynasonde/digisonde/datatypes/mmmdatatypes.py
pynasonde/digisonde/datatypes/rsfdatatypes.py
pynasonde/digisonde/datatypes/saoxmldatatypes.py
pynasonde/digisonde/datatypes/sbfdatatypes.py
pynasonde/digisonde/parsers/__init__.py
pynasonde/digisonde/parsers/dft.py
pynasonde/digisonde/parsers/dvl.py
pynasonde/digisonde/parsers/edp.py
pynasonde/digisonde/parsers/image_parser.py
pynasonde/digisonde/parsers/mmm.py
pynasonde/digisonde/parsers/rsf.py
pynasonde/digisonde/parsers/sao.py
pynasonde/digisonde/parsers/sbf.py
pynasonde/digisonde/parsers/sky.py
pynasonde/digisonde/raw/__init__.py
pynasonde/digisonde/raw/iq_reader.py
pynasonde/digisonde/raw/iqstream_afrl.py
pynasonde/digisonde/raw/parse.py
pynasonde/digisonde/raw/raw_parse.py
pynasonde/digisonde/raw/raw_plots.py
pynasonde/model/__init__.py
pynasonde/model/igrf.py
pynasonde/model/iri.py
pynasonde/model/msise.py
pynasonde/model/plots.py
pynasonde/model/point.py
pynasonde/model/absorption/__init__.py
pynasonde/model/absorption/collisions.py
pynasonde/model/absorption/constants.py
pynasonde/model/absorption/dispersion_relations.py
pynasonde/model/ionort/__init__.py
pynasonde/model/ionort/ionort_2d.py
pynasonde/model/polan/__init__.py
pynasonde/model/polan/datasets.py
pynasonde/model/polan/polan.py
pynasonde/model/polan/polan_utils.py
pynasonde/model/trace/__init__.py
pynasonde/model/trace/homing.py
pynasonde/model/trace/ionosphere.py
pynasonde/model/trace/plottrace.py
pynasonde/model/trace/rt2d.py
pynasonde/vipir/__init__.py
pynasonde/vipir/ngi/__init__.py
pynasonde/vipir/ngi/plotlib.py
pynasonde/vipir/ngi/scale.py
pynasonde/vipir/ngi/source.py
pynasonde/vipir/ngi/utils.py
pynasonde/vipir/riq/__init__.py
pynasonde-1.0.0.dist-info/LICENSE
pynasonde-1.0.0.dist-info/METADATA
pynasonde-1.0.0.dist-info/WHEEL
pynasonde-1.0.0.dist-info/top_level.txt
pynasonde-1.0.0.dist-info/RECORD
