Metadata-Version: 2.1
Name: pynasonde
Version: 1.0.0
Summary: Precision ionospheric radio sounding tools
Home-page: https://github.com/shibaji7/pynasonde
Author: Shibaji Chakraborty
Author-email: chakras4@erau.edu
Maintainer: Shibaji Chakraborty
Maintainer-email: chakras4@erau.edu
License: MIT
Requires-Python: >=3.11
License-File: LICENSE
Provides-Extra: dev
Requires-Dist: pytest; extra == "dev"
Requires-Dist: pytest-cov; extra == "dev"
Requires-Dist: coverage; extra == "dev"
Requires-Dist: numpy; extra == "dev"
Requires-Dist: pandas; extra == "dev"
Requires-Dist: matplotlib; extra == "dev"
Requires-Dist: opencv-python-headless; extra == "dev"
Requires-Dist: pytesseract; extra == "dev"
Requires-Dist: loguru; extra == "dev"
Requires-Dist: requests; extra == "dev"
Requires-Dist: beautifulsoup4; extra == "dev"
Requires-Dist: tqdm; extra == "dev"
Requires-Dist: lxml; extra == "dev"
Requires-Dist: toml; extra == "dev"
Requires-Dist: pytz; extra == "dev"
Requires-Dist: timezonefinder; extra == "dev"
Requires-Dist: SciencePlots; extra == "dev"
Requires-Dist: scipy; extra == "dev"
